LICENSE
README.md
pandas_aws/__init__.py
pandas_aws/s3.py
pandas_aws-0.1.6.dist-info/LICENSE
pandas_aws-0.1.6.dist-info/WHEEL
pandas_aws-0.1.6.dist-info/METADATA
pandas_aws-0.1.6.dist-info/RECORD
