Metadata-Version: 2.1
Name: pandas-aws
Version: 0.1.6
Summary: 
Home-page: https://github.com/FlorentPajot/pandas-aws
License: MIT
Keywords: pandas,aws,python,dataengineering
Author: FlorentPajot
Author-email: pro.florent.pajot@gmail.com
Requires-Python: >=3.6.1,<3.9.0
Classifier: License :: OSI Approved :: MIT License
Classifier: Operating System :: OS Independent
Classifier: Programming Language :: Python :: 3
Classifier: Programming Language :: Python :: 3 :: Only
Classifier: Programming Language :: Python :: 3.7
Classifier: Programming Language :: Python :: 3.8
Classifier: Topic :: Scientific/Engineering
Classifier: Topic :: Scientific/Engineering :: Artificial Intelligence
Classifier: Topic :: Software Development :: Libraries :: Python Modules
Requires-Dist: boto3 (>=1.12.26,<2.0.0)
Requires-Dist: fastparquet (>=0.3.3,<0.5.0)
Requires-Dist: pandas (>=0.23.3,<2.0.0)
Requires-Dist: psycopg2 (>=2.8.6,<3.0.0)
Requires-Dist: pyarrow (>=0.16.0,<0.17.0)
Requires-Dist: xlrd (>=1.2.0,<2.0.0)
Requires-Dist: xlsxwriter (>=1.2.8,<2.0.0)
Project-URL: Repository, https://github.com/FlorentPajot/pandas-aws
